

[
    {
        "identificacion": "1023593299",
        "nombres": "Santiago",
        "apellidos": "Avendaño Upegui"
    },
    {
        "identificacion": "1021806320",
        "nombres": "Santiago ",
        "apellidos": "Zapata Villada"
    },
    {
        "identificacion": "1020419160",
        "nombres": "samuel",
        "apellidos": "martinez guzman",
        "grupo": "b1-martes"
    },
    {
        "identificacion": "1020419160",
        "nombres": "Juan Diego",
        "apellidos": "Cano Galeano",
        "grupo": "b1-martes"
    }
]

